{
  "articleType" : 0,
  "attachments" : [

  ],
  "cids" : {

  },
  "content" : "## 掌櫃也畫餅\n人家穿越都是男主女主，再不濟也是什麼反派惡毒女配，怎麼到我這就是小客棧老闆。難道是要我專心搞事業？這破客棧連賦稅都繳不起了。\n\n廚房夥計大陸，剛好買菜回來。\n\n「大陸大陸，過來過來，我問問你。」\n\n大陸操著一口很濃的地方口音湊過來說：「掌櫃的，找俺什麼事」\n\n「我問你，你認識我的父母嗎？」\n\n「俺知道，你經常說你父母雙亡，被你哥坑害才白手起家，然後用全部家當來這開客棧，要俺們多跟你學習。」\n\n父母雙亡，沒車沒房，愛給員工畫餅是吧。\n\n「啊哈哈哈哈，很好大陸，你記得很棒。年輕人要多吃苦，客棧今年如果收益好，我年末就給你分……加工錢。或者晉升你成為我們緣來客棧的後勤部總領班！」 我亢奮的說完，拍了拍大陸的肩膀。\n\n「真噠？誒那太好了！」\n\n「先去忙吧」\n\n前領導的話真好使，這餅也得古人吃吃。\n\n[#緣來客棧](緣來客棧.html)",
  "contentRendered" : "<h2>掌櫃也畫餅</h2>\n<p>人家穿越都是男主女主，再不濟也是什麼反派惡毒女配，怎麼到我這就是小客棧老闆。難道是要我專心搞事業？這破客棧連賦稅都繳不起了。</p>\n<p>廚房夥計大陸，剛好買菜回來。</p>\n<p>「大陸大陸，過來過來，我問問你。」</p>\n<p>大陸操著一口很濃的地方口音湊過來說：「掌櫃的，找俺什麼事」</p>\n<p>「我問你，你認識我的父母嗎？」</p>\n<p>「俺知道，你經常說你父母雙亡，被你哥坑害才白手起家，然後用全部家當來這開客棧，要俺們多跟你學習。」</p>\n<p>父母雙亡，沒車沒房，愛給員工畫餅是吧。</p>\n<p>「啊哈哈哈哈，很好大陸，你記得很棒。年輕人要多吃苦，客棧今年如果收益好，我年末就給你分……加工錢。或者晉升你成為我們緣來客棧的後勤部總領班！」 我亢奮的說完，拍了拍大陸的肩膀。</p>\n<p>「真噠？誒那太好了！」</p>\n<p>「先去忙吧」</p>\n<p>前領導的話真好使，這餅也得古人吃吃。</p>\n<p><a href=\"%E7%B7%A3%E4%BE%86%E5%AE%A2%E6%A3%A7.html\">#緣來客棧</a></p>\n",
  "created" : 778344906.84396,
  "externalLink" : "",
  "hasAudio" : false,
  "hasVideo" : false,
  "id" : "D01E4B5C-9A62-4AC7-864B-5D42610ABF29",
  "link" : "/D01E4B5C-9A62-4AC7-864B-5D42610ABF29/",
  "slug" : "",
  "tags" : {

  },
  "title" : ""
}